unirec/__init__.py
unirec/config/base.yaml
unirec/config/dataset/Beauty-libfm.yaml
unirec/config/dataset/Beauty-rank.yaml
unirec/config/dataset/Beauty.yaml
unirec/config/dataset/DE_final_dataset.yaml
unirec/config/dataset/DE_final_next_item_dataset.yaml
unirec/config/dataset/ES_final_dataset.yaml
unirec/config/dataset/ES_final_next_item_dataset.yaml
unirec/config/dataset/FR_final_dataset.yaml
unirec/config/dataset/FR_final_next_item_dataset.yaml
unirec/config/dataset/IT_final_dataset.yaml
unirec/config/dataset/IT_final_next_item_dataset.yaml
unirec/config/dataset/JP_final_dataset.yaml
unirec/config/dataset/JP_final_next_item_dataset.yaml
unirec/config/dataset/Steam.yaml
unirec/config/dataset/UK_final_dataset.yaml
unirec/config/dataset/UK_final_next_item_dataset.yaml
unirec/config/dataset/amazon-book.yaml
unirec/config/dataset/amazon-electronics.yaml
unirec/config/dataset/app-store.yaml
unirec/config/dataset/cikmcup.yaml
unirec/config/dataset/example.yaml
unirec/config/dataset/gowalla.yaml
unirec/config/dataset/ml-100k-libfm.yaml
unirec/config/dataset/ml-100k-rank.yaml
unirec/config/dataset/ml-100k.yaml
unirec/config/dataset/ml-25m-retrieval.yaml
unirec/config/dataset/ml-25m-retrieval_firstlines.yaml
unirec/config/dataset/yelp2018.yaml
unirec/config/model/AdmmSLIM.yaml
unirec/config/model/AttHist.yaml
unirec/config/model/AvgHist.yaml
unirec/config/model/BST.yaml
unirec/config/model/ConvFormer.yaml
unirec/config/model/EASE.yaml
unirec/config/model/FASTConvFormer.yaml
unirec/config/model/FM.yaml
unirec/config/model/GRU4Rec.yaml
unirec/config/model/MF.yaml
unirec/config/model/MultiVAE.yaml
unirec/config/model/SAR.yaml
unirec/config/model/SASRec.yaml
unirec/config/model/SLIM.yaml
unirec/config/model/SVDPlusPlus.yaml
unirec/config/model/UserCF.yaml
unirec/constants/__init__.py
unirec/constants/global_variables.py
unirec/constants/loss_funcs.py
unirec/constants/protocols.py
unirec/data/__init__.py
unirec/data/dataloader/__init__.py
unirec/data/dataloader/basedataloader.py
unirec-0.0.1a4.dist-info/LICENSE.txt
unirec-0.0.1a4.dist-info/METADATA
unirec-0.0.1a4.dist-info/WHEEL
unirec-0.0.1a4.dist-info/top_level.txt
unirec-0.0.1a4.dist-info/RECORD
