Metadata-Version: 2.1
Name: unirec
Version: 0.0.1a4
Summary: A compact recommender library for universal recommendation systems
Home-page: 
Author: Jianxun Lian
Author-email: jialia@microsoft.com
License: MIT
Keywords: recommender system,deep learning,pytorch
Classifier: Development Status :: 3 - Alpha
Classifier: Intended Audience :: Developers
Classifier: Intended Audience :: Science/Research
Classifier: Environment :: GPU :: NVIDIA CUDA
Classifier: Programming Language :: Python :: 3
Classifier: Programming Language :: Python :: 3
Classifier: Programming Language :: Python :: 3.8
Classifier: Programming Language :: Python :: 3.9
Classifier: Programming Language :: Python :: 3.10
Classifier: Operating System :: OS Independent
Classifier: Natural Language :: English
Classifier: License :: OSI Approved :: MIT License
Classifier: Topic :: Scientific/Engineering :: Artificial Intelligence
Requires-Python: >=3.8
License-File: LICENSE.txt
Requires-Dist: torch <=1.13.1,>=1.10.0
Requires-Dist: debugpy >=1.6.3
Requires-Dist: feather-format >=0.4.1
Requires-Dist: numba >=0.56.3
Requires-Dist: pandas >=1.5.1
Requires-Dist: pyarrow >=10.0.0
Requires-Dist: scikit-learn >=1.1.3
Requires-Dist: scipy >=1.9.3
Requires-Dist: setproctitle >=1.3.2
Requires-Dist: swifter >=1.3.4
Requires-Dist: tqdm >=4.64.1
Requires-Dist: wandb >=0.14.2
Requires-Dist: tensorboard >=2.13.0
Requires-Dist: cvxpy ==1.3.1
Requires-Dist: onnxruntime >=1.15.1
Requires-Dist: accelerate >=0.20.3
Requires-Dist: pytest >=7.3.1
